{"Korean court music": "600", "Bardcore": "2010", "Minimal music": "1960", "Danger music": "1960", "Drone music": "1960", "Industrial music": "1970", "Blues rock": "1960", "Desert blues": "1980", "Electric blues": "1930", "Jump blues": "1930", "Louisiana blues": "1940", "Memphis blues": "1910", "New Orleans blues": "1940", "Piedmont blues": "1920", "Punk blues": "1980", "Rhythm and blues": "1940", "Doo-wop": "1940", "Soul blues": "1950", "Swamp blues": "1950", "Texas blues": "1900", "West Coast blues": "1940", "Cowpunk": "1970", "Americana (music)": "1900", "Bakersfield sound": "1950", "Bluegrass music": "1940", "Country pop": "1960", "Country rap": "1990", "Country rock": "1960", "Dansband": "1970", "Gothic country": "1990", "Country music": "1920", "Nashville sound": "1950", "Outlaw country": "1960", "Progressive country": "1960", "Rockabilly": "1950", "Psychobilly": "1970", "Sertanejo music": "1920", "Texas country music": "1960", "Truck-driving country": "1960", "Cowboy pop": "1970", "Western swing": "1920", "Downtempo": "1980", "Light music": "1900", "Lounge music": "1950", "New-age music": "1960", "Ambient music": "1960", "Dark ambient": "1980", "Dungeon synth": "1990", "Illbient": "1990", "Space music": "1970", "Onkyokei": "1990", "Footwork (genre)": "1990", "Future bass": "2010", "UK bass": "2000", "Wave music": "2010", "Breakbeat": "1970", "Baltimore club": "1990", "Jersey club": "2000", "Big beat": "1990", "Breakbeat hardcore": "1980", "Darkcore": "1990", "Broken beat": "1990", "Florida breaks": "1980", "Psydub": "1990", "Chopped and screwed": "1990", "Disco": "1960", "Afro/cosmic music": "1970", "Hi-NRG": "1970", "Eurobeat": "1980", "Eurodance": "1980", "Italo dance": "1990", "Italo disco": "1970", "Eurodisco": "1970", "Nu-disco": "1990", "Post-disco": "1970", "Boogie (genre)": "1970", "City pop": "1970", "Drum and bass": "1990", "Hardstep": "1990", "Liquid funk": "1999", "Neurofunk": "1990", "Sambass": "2000", "Techstep": "1990", "Dub music": "1960", "Dub poetry": "1970", "Dubtronica": "1980", "Electronic rock": "1960", "Dance-rock": "1970", "Alternative dance": "1980", "Baggy": "1980", "New rave": "2000", "Dance-punk": "1970", "Krautrock": "1960", "New wave music": "1970", "Cold wave (music)": "1970", "Dark wave": "1970", "Neoclassical dark wave": "1980", "Neue Deutsche Todeskunst": "1980", "Ethereal wave": "1980", "Minimal wave": "1970", "Neue Deutsche Welle": "1970", "New wave of new wave": "1990", "Sophisti-pop": "1980", "Synth-pop": "1977", "Dance-pop": "1970", "Disco polo": "1980", "Electroclash": "1990", "Electropop": "1980", "Hyperpop": "2010", "Post-rock": "1980", "Space rock": "1960", "Electronicore": "2000", "Electronica": "1990", "Folktronica": "1990", "Ethnic electronica": "1980", "Afrobeats": "2000", "Coup\u00e9-d\u00e9cal\u00e9": "2000", "Mahraganat": "2000", "Budots": "2009", "Changa tuki": "1990", "Dancehall pop": "2000", "Funk carioca": "1980", "Funk ostenta\u00e7\u00e3o": "2000", "Proibid\u00e3o": "1990", "Rasteirinha": "2012", "Merenhouse": "1990", "Rab\u00f2day": "2000", "Rara tech": "2010", "Russ music": "2000", "Tribal guarachero": "2000", "Worldbeat": "1980", "Manila sound": "1970", "Funk": "1960", "Acid jazz": "1980", "Jungle music": "1990", "Hardcore (electronic dance music genre)": "1980", "Bouncy techno": "1990", "Breakcore": "1990", "Digital hardcore": "1990", "Frenchcore": "1990", "Gabber": "1990", "Mainstream hardcore": "1990", "Happy hardcore": "1990", "J-core": "1990", "Lento violento": "1990", "M\u00e1kina": "1990", "Hardstyle": "1990", "Jumpstyle": "1990", "Chillwave": "2000", "Hypnagogic pop": "2000", "Synthwave": "2000", "Sovietwave": "2010", "Vaporwave": "2010", "Dreampunk": "2010", "Hardvapour": "2015", "Mallsoft": "2010", "Seapunk": "2011", "Hip hop music": "1973", "Afroswing": "2010", "Alternative hip hop": "1980", "Hipster hop": "2000", "Cloud rap": "2000", "Crunk": "1990", "Crunkcore": "2000", "Snap music": "2000", "Electro (music)": "1970", "Emo rap": "2010", "Lofi hip hop": "2000", "Miami bass": "1980", "Mumble rap": "2010", "Trap music": "1990", "Drill music": "2010", "UK drill": "2010", "Latin trap": "2000", "Phonk": "2010", "House music": "1980", "Acid house": "1985", "Amapiano": "2010", "Gqom": "2010", "Kidandali": "1990", "Kwaito": "1980", "Ambient house": "1980", "Balearic beat": "1980", "Chicago house": "1983", "Deep house": "1985", "Diva house": "1990", "Hardbag": "1990", "Big room house": "2000", "Electro swing": "1990", "French house": "1990", "Funky house": "1980", "Future house": "2013", "Garage house": "1983", "Ghetto house": "1980", "Ghettotech": "1990", "Hip house": "1980", "Italo house": "1980", "Latin house": "1980", "Microhouse": "1990", "Moombahton": "2009", "New Jersey sound": "1980", "Outsider house": "2010", "Progressive house": "1990", "Tech house": "1986", "Tribal house": "1980", "Tropical house": "2010", "UK hard house": "1990", "Hard NRG": "1990", "Hardbass": "1990", "Deconstructed club": "2000", "Electro-industrial": "1980", "Electronic body music": "1980", "Futurepop": "1990", "New beat": "1980", "Industrial hip hop": "1980", "Industrial metal": "1980", "Neue Deutsche H\u00e4rte": "1990", "Industrial rock": "1980", "Intelligent dance music": "1990", "Drill 'n' bass": "1990", "Glitch (music)": "1990", "Neo soul": "1980", "Nightcore": "2001", "Noise music": "1910", "Harsh noise wall": "1990", "Japanoise": "1970", "Noise pop": "1980", "Power electronics (music)": "1970", "Power noise": "1990", "Plunderphonics": "1980", "Sampledelia": "1960", "Techno": "1980", "Acid techno": "1980", "Ambient techno": "1980", "Birmingham sound": "1990", "Bleep techno": "1980", "Detroit techno": "1980", "Dub techno": "1990", "Industrial techno": "1990", "Minimal techno": "1990", "Schaffel": "1990", "Toytown techno": "1990", "Tecno brega": "2000", "Trance music": "1980", "Acid trance": "1990", "Balearic trance": "1990", "Dream trance": "1990", "Goa trance": "1990", "Nitzhonot": "1990", "Hard trance": "1990", "Psychedelic trance": "1990", "Suomisaundi": "1990", "Tech trance": "1990", "Uplifting trance": "1990", "Vocal trance": "1990", "UK garage": "1990", "2-step garage": "1990", "Bassline (music genre)": "2000", "Breakstep": "1990", "Dubstep": "2000", "Post-dubstep": "2000", "Reggaestep": "2000", "Future garage": "2000", "Grime music": "2000", "Speed garage": "1990", "UK funky": "2000", "Funkstep": "2000", "Chiptune": "1970", "Bitpop": "1990", "Nintendocore": "2000", "Skweee": "2000", "Anti-folk": "1980", "Chalga": "1960", "Folk rock": "1960", "Celtic rock": "1960", "Indie folk": "1990", "Industrial folk music": "1700", "Neofolk": "1980", "Psychedelic folk": "1960", "Nueva canci\u00f3n": "1960", "Boom bap": "1980", "Bounce music": "1980", "Chopper (rap)": "1990", "Comedy hip hop": "1990", "East Coast hip hop": "1973", "G-funk": "1990", "Hardcore hip hop": "1980", "Dirty rap": "1970", "Horrorcore": "1981", "Memphis rap": "1980", "Hip hop soul": "1992", "Hyphy": "1990", "Jerkin'": "2000", "Jazz rap": "1980", "Latin hip hop": "1970", "Nerdcore": "1990", "Chap hop": "2000", "New jack swing": "1980", "Political hip hop": "1980", "Pop rap": "1980", "Progressive rap": "1980", "Punk rap": "2000", "Rap rock": "1980", "Rap metal": "1980", "Christian hip hop": "1980", "Jewish hip hop": "2000", "Southern hip hop": "1980", "Brooklyn drill": "2010", "West Coast hip hop": "1970", "Avant-garde jazz": "1950", "Bebop": "1940", "Big band": "1910", "Bossa nova": "1950", "Cape jazz": "1950", "Chamber jazz": "1960", "Cool jazz": "1940", "Free funk": "1970", "Free improvisation": "1960", "Free jazz": "1950", "Gypsy jazz": "1934", "Hard bop": "1950", "Jazz-funk": "1960", "Jazz fusion": "1960", "Kansas City jazz": "1920", "Modal jazz": "1950", "Nu jazz": "1990", "Punk jazz": "1970", "Samba-jazz": "1950", "Shibuya-kei": "1990", "Smooth jazz": "1970", "Soul jazz": "1950", "Straight-ahead jazz": "1960", "Swing music": "1930", "West Coast jazz": "1940", "Arabic pop music": "1970", "Art pop": "1960", "Baroque pop": "1960", "Beach music": "1950", "Brill Building (genre)": "1950", "Britpop": "1990", "Hokkien pop": "1930", "Mandopop": "1920", "Chamber pop": "1960", "Cringe pop": "2010", "Europop": "1960", "Austropop": "1960", "French pop music": "1950", "Nederpop": "1960", "Russian pop": "1950", "Indie pop": "1970", "Indian pop": "1960", "J-pop": "1980", "Anime song": "1970", "Jangle pop": "1950", "K-pop": "1940", "Korean hip hop": "1980", "Latin ballad": "1960", "Latin pop": "1970", "Mexican pop music": "1930", "New Pop": "1980", "Pinoy pop": "1970", "Pop rock": "1950", "Emo pop": "1990", "Power pop": "1960", "Soft rock": "1960", "Yacht rock": "1970", "Progressive pop": "1960", "Psychedelic pop": "1960", "Schlager music": "1950", "Space age pop": "1950", "Sunshine pop": "1960", "Swamp pop": "1950", "Teen pop": "1980", "Turbo-folk": "1970", "Vispop": "1960", "Wonky pop": "2000", "Y\u00e9-y\u00e9": "1960", "Classic soul": "1960", "Freestyle music": "1980", "Go-go": "1960", "Deep funk": "1960", "Psychedelic funk": "1960", "Soul music": "1950", "Cinematic soul": "1970", "Northern soul": "1960", "Progressive soul": "1960", "Psychedelic soul": "1960", "Quiet storm": "1970", "Southern soul": "1950", "Adult album alternative": "1980", "Alternative rock": "1970", "Post-Britpop": "1990", "Dream pop": "1980", "Shoegaze": "1980", "Blackgaze": "2000", "Grunge": "1980", "Post-grunge": "1990", "Soft grunge": "2010", "Indie rock": "1980", "Dunedin sound": "1980", "Math rock": "1980", "Midwest emo": "1990", "Post-punk revival": "1990", "Slacker rock": "1980", "Slowcore": "1990", "Anatolian rock": "1950", "Arena rock": "1960", "Beat music": "1950", "Freakbeat": "1960", "Nederbeat": "1960", "Boogie rock": "1960", "Brazilian rock": "1950", "Samba rock": "1950", "Christian rock": "1960", "Comedy rock": "1950", "Dark cabaret": "1980", "Death 'n' roll": "1993", "Palm Desert Scene": "1990", "Experimental rock": "1960", "Art rock": "1960", "Post-punk": "1970", "Gothic rock": "1970", "No wave": "1970", "Post-metal": "1990", "British folk rock": "1960", "Medieval folk rock": "1960", "Funk rock": "1960", "Garage rock": "1950", "Proto-punk": "1960", "Geek rock": "1990", "Glam rock": "1970", "Pagan rock": "1975", "Hard rock": "1960", "Heartland rock": "1970", "Heavy metal music": "1960", "Iranian rock": "1960", "Instrumental rock": "1950", "Latin rock": "1950", "Mangue bit": "1990", "Occult rock": "1960", "Paisley Underground": "1980", "Progressive rock": "1960", "Avant-prog": "1970", "Canterbury scene": "1960", "Flamenco rock": "1960", "Neo-progressive rock": "1980", "Post-progressive": "1978", "Proto-prog": "1960", "Zeuhl": "1960", "Psychedelic rock": "1960", "Acid rock": "1960", "Neo-psychedelia": "1970", "Raga rock": "1960", "Pub rock (Australia)": "1970", "Pub rock (United Kingdom)": "1970", "Punk rock": "1970", "Reggae rock": "1970", "Rock and roll": "1940", "Gothabilly": "1970", "Roots rock": "1960", "Southern rock": "1960", "Stoner rock": "1990", "Swamp rock": "1960", "Sufi rock": "1990", "Visual kei": "1980", "Nagoya kei": "1990", "Wizard rock": "2000", "Alternative metal": "1980", "Funk metal": "1980", "Nu metal": "1990", "Avant-garde metal": "1980", "Drone metal": "1990", "Black metal": "1980", "Blackened death metal": "1990", "National Socialist black metal": "1990", "Symphonic black metal": "1990", "Viking metal": "1980", "Christian metal": "1970", "Unblack metal": "1990", "Death metal": "1980", "Melodic death metal": "1990", "Technical death metal": "1980", "Doom metal": "1970", "Death-doom": "1980", "Extreme metal": "1980", "Folk metal": "1990", "Celtic metal": "1990", "Medieval metal": "1990", "Pagan metal": "1990", "Glam metal": "1970", "Gothic metal": "1990", "Kawaii metal": "2010", "Latin metal": "1970", "Mathcore": "1990", "Metalcore": "1990", "Deathcore": "1990", "Melodic metalcore": "1990", "Progressive metalcore": "1990", "Neoclassical metal": "1970", "New wave of American heavy metal": "1990", "Pirate metal": "1980", "Pop metal": "1970", "Power metal": "1980", "Progressive metal": "1980", "Djent": "1990", "Sludge metal": "1980", "Speed metal": "1970", "Symphonic metal": "1990", "Thrash metal": "1980", "Crossover thrash": "1980", "Groove metal": "1990", "Crust punk": "1980", "D-beat": "1980", "Art punk": "1970", "Christian punk": "1980", "Folk punk": "1980", "Celtic punk": "1980", "Gypsy punk": "1990", "Garage punk (fusion genre)": "1980", "Glam punk": "1970", "Grindcore": "1980", "Goregrind": "1980", "Pornogrind": "1990", "Hardcore punk": "1970", "Beatdown hardcore": "1990", "Christian hardcore": "1980", "Melodic hardcore": "1980", "Positive hardcore": "1980", "Post-hardcore": "1980", "Queercore": "1980", "Taqwacore": "1990", "Screamo": "1990", "Powerviolence": "1980", "Street punk": "1980", "Horror punk": "1970", "Nazi punk": "1970", "Oi!": "1970", "Punk pathetique": "1970", "Reggae punk": "1970", "Riot grrrl": "1990", "Ska punk": "1970", "Skate punk": "1980", "Trallpunk": "1980", "African heavy metal": "1970", "Afrobeat": "1960", "Apala": "1930", "Arabesque (Turkish music)": "1940", "Benga music": "1940", "Bikutsi": "1940", "Boomba music": "1990", "Chimurenga music": "1970", "Congolese rumba": "1930", "Fuji music": "1500", "Genge": "1990", "Gumbe": "1980", "Highlife": "1870", "Hiplife": "1990", "Igbo highlife": "1870", "Igbo rap": "1990", "Jit": "1980", "J\u00f9j\u00fa music": "1900", "Kadongo Kamu": "1960", "Kizomba": "1984", "Makossa": "1950", "Marabi": "1920", "Marrabenta": "1930", "Mbalax": "1970", "Mbaqanga": "1960", "Mbube (genre)": "1930", "Ndombolo": "1990", "Palm-wine music": "1920", "Sakara music": "1930", "Soukous": "1960", "Zamrock": "1960", "Zouglou": "1990", "Ragtime": "1890", "Stride (music)": "1920", "Enka": "1950", "Japanese hip hop": "1980", "Kay\u014dkyoku": "1920", "Bhangra (music)": "1960", "Sri Lankan hip hop": "1990", "Malaysian hip hop": "1980", "Dangdut": "1970", "Indo pop": "1960", "Luk thung": "1930", "Thai pop music": "1950", "Pinoy rock": "1950", "V-pop": "1980", "Bouyon music": "1980", "Cadence-lypso": "1970", "Chutney soca": "1980", "Compas": "1955", "Dancehall": "1970", "Mambo (music)": "1930", "Rasin": "1977", "Reggae": "1960", "Ragga": "1980", "Reggae fusion": "1970", "Reggaeton": "1980", "Rocksteady": "1960", "Rhumba": "1930", "Ska": "1950", "Two-tone (music genre)": "1970", "Soca music": "1970", "Timba": "1988", "Zouk": "1980", "M\u00fasica popular brasileira": "1960", "Pagode": "1970", "Boogaloo": "1960", "Grupera": "1970", "Bolero": "1880", "Tropipop": "1980", "Urbano music": "1980", "Vallenato": "1900", "Contemporary Christian music": "1960", "Contemporary worship music": "1950", "Styles of pop music": "1990"}